setup.py
inference_basic/__init__.py
inference_basic/config.py
inference_basic/model_activation.py
inference_basic/small_inference.py
inference_basic/utils.py
inference_small.egg-info/PKG-INFO
inference_small.egg-info/SOURCES.txt
inference_small.egg-info/dependency_links.txt
inference_small.egg-info/not-zip-safe
inference_small.egg-info/top_level.txt