Metadata-Version: 2.1
Name: inference-small
Version: 0.1
Summary: inference for basic image
Home-page: UNKNOWN
Author: Uria Levkovitz
Author-email: urialevko@gmail.com
License: UNKNOWN
Platform: UNKNOWN
